nile_upgrades/artifacts/Proxy.json
nile_upgrades/common.py
nile_upgrades/deploy_proxy.py
nile_upgrades/upgrade_proxy.py
nile_upgrades-0.0.3.dist-info/LICENSE
nile_upgrades-0.0.3.dist-info/WHEEL
nile_upgrades-0.0.3.dist-info/entry_points.txt
nile_upgrades-0.0.3.dist-info/METADATA
nile_upgrades-0.0.3.dist-info/RECORD
