Metadata-Version: 2.1
Name: nile-upgrades
Version: 0.0.3
Summary: Nile plugin to deploy and manage upgradeable smart contracts on StarkNet
Home-page: https://github.com/OpenZeppelin/openzeppelin-nile-upgrades
License: MIT
Keywords: cairo,nile
Author: Eric Lau
Author-email: ericglau@outlook.com
Requires-Python: >=3.8,<3.10
Classifier: Development Status :: 3 - Alpha
Classifier: Intended Audience :: Developers
Classifier: License :: OSI Approved :: MIT License
Classifier: Operating System :: OS Independent
Classifier: Programming Language :: Python :: 3
Classifier: Programming Language :: Python :: 3.8
Classifier: Programming Language :: Python :: 3.9
Classifier: Topic :: Software Development :: Libraries :: Python Modules
Requires-Dist: click (>=8.0.4,<9.0.0)
Project-URL: Repository, https://github.com/OpenZeppelin/openzeppelin-nile-upgrades
